django_web_exceptions-0.1.4.dist-info/DESCRIPTION.rst
django_web_exceptions-0.1.4.dist-info/METADATA
django_web_exceptions-0.1.4.dist-info/RECORD
django_web_exceptions-0.1.4.dist-info/WHEEL
django_web_exceptions-0.1.4.dist-info/metadata.json
django_web_exceptions-0.1.4.dist-info/top_level.txt
web_exceptions/__init__.py
web_exceptions/exceptions.py
web_exceptions/middleware.py
