Metadata-Version: 2.0
Name: django-web-exceptions
Version: 0.1.4
Summary: Throwing web exceptions like in AioHTTP
Home-page: https://github.com/samael500/web-exceptions
Author: Maks Skorokhod
Author-email: samael500@gmail.com
License: MIT
Keywords: web-exceptions,django,web,exceptions,http,response
Platform: UNKNOWN
Classifier: Development Status :: 3 - Alpha
Classifier: Framework :: Django
Classifier: Framework :: Django :: 1.10
Classifier: Intended Audience :: Developers
Classifier: License :: OSI Approved :: MIT License
Classifier: Natural Language :: English
Classifier: Programming Language :: Python :: 3
Classifier: Programming Language :: Python :: 3.4
Classifier: Programming Language :: Python :: 3.5
Requires-Dist: Django (>=1.10)
